debugbuddy/__init__.py
debugbuddy/__main__.py
debugbuddy/__version__.py
debugbuddy/cli.py
debugbuddy/cli/__init__.py
debugbuddy/cli/formatters.py
debugbuddy/cli/validators.py
debugbuddy/cli/commands/__init__.py
debugbuddy/cli/commands/check.py
debugbuddy/cli/commands/config.py
debugbuddy/cli/commands/explain.py
debugbuddy/cli/commands/github.py
debugbuddy/cli/commands/history.py
debugbuddy/cli/commands/predict.py
debugbuddy/cli/commands/search.py
debugbuddy/cli/commands/train.py
debugbuddy/cli/commands/watch.py
debugbuddy/core/__init__.py
debugbuddy/core/explainer.py
debugbuddy/core/predictor.py
debugbuddy/core/trainer.py
debugbuddy/core/parsers/__init__.py
debugbuddy/core/parsers/base.py
debugbuddy/core/parsers/c.py
debugbuddy/core/parsers/java.py
debugbuddy/core/parsers/javascript.py
debugbuddy/core/parsers/php.py
debugbuddy/core/parsers/python.py
debugbuddy/core/parsers/ruby.py
debugbuddy/core/parsers/typescript.py
debugbuddy/integrations/__init__.py
debugbuddy/integrations/ai/__init__.py
debugbuddy/integrations/ai/anthropic.py
debugbuddy/integrations/ai/base.py
debugbuddy/integrations/ai/grok.py
debugbuddy/integrations/ai/openai.py
debugbuddy/integrations/ai/prompts.py
debugbuddy/integrations/github/__init__.py
debugbuddy/integrations/github/client.py
debugbuddy/integrations/github/issues.py
debugbuddy/integrations/github/search.py
debugbuddy/models/__init__.py
debugbuddy/models/error.py
debugbuddy/models/ml_engine.py
debugbuddy/models/pattern.py
debugbuddy/models/prediction.py
debugbuddy/models/training.py
debugbuddy/monitoring/__init__.py
debugbuddy/monitoring/analyzer.py
debugbuddy/monitoring/checker.py
debugbuddy/monitoring/watcher.py
debugbuddy/storage/__init__.py
debugbuddy/storage/cache.py
debugbuddy/storage/config.py
debugbuddy/storage/history.py
debugbuddy/storage/patterns.py
debugbuddy/tui/__init__.py
debugbuddy/tui/app.py
debugbuddy/tui/runner.py
debugbuddy/tui/shell.py
debugbuddy/tui/views.py
debugbuddy/tui/watch.py
debugbuddy/utils/__init__.py
debugbuddy_cli-0.4.7.dist-info/licenses/LICENSE
debugbuddy_cli-0.4.7.dist-info/METADATA
debugbuddy_cli-0.4.7.dist-info/WHEEL
debugbuddy_cli-0.4.7.dist-info/entry_points.txt
debugbuddy_cli-0.4.7.dist-info/top_level.txt
debugbuddy_cli-0.4.7.dist-info/RECORD
