Metadata-Version: 2.4
Name: debugbuddy-cli
Version: 0.4.7
Summary: Your terminal's debugging companion - instant error explanations
Home-page: https://github.com/DevArqf/DeBugBuddy
Download-URL: https://github.com/DevArqf/DeBugBuddy/archive/refs/tags/v0.4.7.tar.gz
Author: DevArqf
Author-email: devarqf@gmail.com
License: MIT
Keywords: python,debugging,cli
Classifier: Development Status :: 3 - Alpha
Classifier: Intended Audience :: Developers
Classifier: Topic :: Software Development :: Debuggers
Classifier: Programming Language :: Python :: 3
Classifier: Programming Language :: Python :: 3.8
Classifier: Programming Language :: Python :: 3.9
Classifier: Programming Language :: Python :: 3.10
Classifier: Programming Language :: Python :: 3.11
Classifier: Programming Language :: Python :: 3.12
Requires-Python: >=3.8
License-File: LICENSE
Requires-Dist: click>=8.0.0
Requires-Dist: rich>=13.0.0
Requires-Dist: textual>=0.55.0
Provides-Extra: ai
Requires-Dist: openai>=2.8.1; extra == "ai"
Requires-Dist: anthropic>=0.18.0; extra == "ai"
Provides-Extra: github
Requires-Dist: PyGithub>=2.1.0; extra == "github"
Provides-Extra: watch
Requires-Dist: watchdog>=3.0.0; extra == "watch"
Provides-Extra: full
Requires-Dist: openai>=2.8.1; extra == "full"
Requires-Dist: anthropic>=0.18.0; extra == "full"
Requires-Dist: PyGithub>=2.1.0; extra == "full"
Requires-Dist: watchdog>=3.0.0; extra == "full"
Dynamic: author
Dynamic: author-email
Dynamic: classifier
Dynamic: description
Dynamic: description-content-type
Dynamic: download-url
Dynamic: home-page
Dynamic: keywords
Dynamic: license
Dynamic: license-file
Dynamic: provides-extra
Dynamic: requires-dist
Dynamic: requires-python
Dynamic: summary
